{
	"configurations" : 
	[
		{
			"directories" : 
			[
				{
					"build" : ".",
					"hasInstallRule" : true,
					"jsonFile" : "directory-.-Debug-c159e2de62a57f4a6fd4.json",
					"minimumCMakeVersion" : 
					{
						"string" : "3.0"
					},
					"projectIndex" : 0,
					"source" : ".",
					"targetIndexes" : 
					[
						0
					]
				}
			],
			"name" : "Debug",
			"projects" : 
			[
				{
					"directoryIndexes" : 
					[
						0
					],
					"name" : "re2dfa",
					"targetIndexes" : 
					[
						0
					]
				}
			],
			"targets" : 
			[
				{
					"directoryIndex" : 0,
					"id" : "re2dfa::@6890427a1f51a3e7e1df",
					"jsonFile" : "target-re2dfa-Debug-50e808064eb41f7fd450.json",
					"name" : "re2dfa",
					"projectIndex" : 0
				}
			]
		}
	],
	"kind" : "codemodel",
	"paths" : 
	{
		"build" : "C:/Users/V4n3k/Documents/code2.0/FLaT/1/cmake-build-debug",
		"source" : "C:/Users/V4n3k/Documents/code2.0/FLaT/1"
	},
	"version" : 
	{
		"major" : 2,
		"minor" : 4
	}
}
